url2word/__init__.py
url2word/__main__.py
url2word-0.1.5.dist-info/DESCRIPTION.rst
url2word-0.1.5.dist-info/METADATA
url2word-0.1.5.dist-info/RECORD
url2word-0.1.5.dist-info/WHEEL
url2word-0.1.5.dist-info/entry_points.txt
url2word-0.1.5.dist-info/metadata.json
url2word-0.1.5.dist-info/top_level.txt
