Metadata-Version: 2.0
Name: url2word
Version: 0.1.5
Summary: get all word in a page
Home-page: UNKNOWN
Author: nil84
Author-email: UNKNOWN
License: Apache License, Version 2.0
Platform: UNKNOWN
Classifier: Programming Language :: Python
Classifier: Programming Language :: Python :: 3.5
Requires-Dist: beautifulsoup4
